[
  {
    "id": 1,
    "name": "Colorful My Future",
    "rank": "10",
    "mv": "9Lh-5xotUeQ",
    "live": "V_yA54dYNLE",
    "call": {
      "Introduction": "スタンダード(倍速)",
      "PreChorus": "チャペアペ虎火ミョーホントゥスケ人造ファイヤファイボワイパー",
      "PostChorus": "ジャパニーズ(倍速)",
      "PreChorus2": "カラキナ除去飛ミョーホントゥスケ人造ファーマ繊維ジャスパー",
      "Interlude": "アイヌ可変アイヌ",
      "Outro": "裏ドイツ逆打ち"
    },
    "calllive": {
      "Introduction": 0,
      "PreChorus": 30,
      "PostChorus": 70,
      "PreChorus2": 100,
      "Interlude": 135,
      "Outro": 195
    },
    "calljump": {
      "Introduction": 12,
      "PreChorus": 52,
      "PostChorus": 80,
      "PreChorus2": 117,
      "Interlude": 145,
      "Outro": 218
    },
    "jide": ["1pre.mp4", "1pre2.mpr", "1inter.mp4", "1out.mp4"],
    "callfull": {
      "Introduction": [
        "(倍速)タイガー ファイヤー サイバー ファイバー",
        "ダイバー バイバー ジャージャー"
      ],
      "PreChorus": [
        "チャペ アペ 虎 火 ミョーホントゥスケ",
        "人造 ファイヤ ファイボ ワイパー"
      ],
      "PostChorus": ["(倍速)虎 火 人造 繊維 海女", "振動 化繊 飛 除去"],
      "PreChorus2": [
        "カラ キナ 除去 飛 ミョーホントゥスケ",
        "人造 ファーマ 繊維 ジャスパー"
      ],
      "Interlude": [
        "チャペ――― アペ―――",
        "（倍速）カラ キナ ララ トゥスケ",
        "（倍速) ウィスゥペ ケスィ スィスゥパ",
        "チャペ アペ カラ キナ ララ ",
        "トゥスケ ミョーホントゥスケ "
      ],
      "Outro": [
        "カール ハインツ シュナイダー(始動)",
        "ヘルマンカルツ",
        "レン ヴァイナハテン ゲッティン",
        "ゼーユングファー バザィディガン",
        "フィリーゲン ヒェーミーファーザー",
        "シュビングング タゥツァー",
        "フィーバー クゥンスト",
        "フォイエル ティーガァ",
        "ゲーエンヴィアー"
      ]
    },
    "lyrics": "空が晴れて太陽の光が差してキラキラ輝く\nColorful My Future\n \n真っ白いままの私の夢のノート\n開いたら何から描こう\nなんでもいいよってペンが走る\n軌跡が色をつけて鮮やかになる\n \n誰にも言えない悩みは塗りつぶして\n彩りの愛を散りばめよう\n \n夢を描いて感情を溢れ出させて続いていくよ色とりどりのMy Story\n空が晴れて太陽の光が差してキラキラ輝く\nColorful My Future\n \n夜が明ける頃 白み始める空\nモノクロに色がついた\nもう独りじゃない みんながいるよ\n書き足していくよ物語の続き\n \n妄想と現実の境で迷っていた\nいま未来へのページをめくる\n \n愛が膨らんで感情が破裂するまで\n何度だってまだ見ぬ明日を描くんだ\n風が運んだ花びらと共に舞える\n煌めくその世界Beautiful My Future\n\nI Wish Forever無限の色\n君とふたり グラデーション\nずっと共に歩むその先まで\n誰も見たことのない世界へと\n\nあの日願った未来は形を変えて\n続いているよ みんなと描くMy Story\n\n夢を描いて感情を溢れ出させて続いていくよ色とりどりのMy Story\n空が晴れて太陽の光が差して\nキラキラ輝く\nColorful My Future"
  },
  {
    "id": 2,
    "name": "Summer Memory",
    "rank": "3",
    "mv": "kdLWr0kRx50",
    "live": "x4w-9Vutytc",
    "call": {
      "Introduction": "スタンダード→園長→逆園長",
      "PostChorus": "ホグワーツ",
      "Verse": "ビスマルク口上",
      "Interlude": "可変三連２",
      "Outro": "ガチ恋キャンセルドイツ三連"
    },
    "calllive": {
      "Introduction": 0,
      "PostChorus": 60,
      "Verse": 90,
      "Interlude": 130,
      "Outro": 180
    },
    "calljump": {
      "Introduction": 0,
      "PostChorus": 70,
      "Verse": 90,
      "Interlude": 140,
      "Outro": 190
    },
    "jide": ["2in.mp4", "2inter.mp4", "2out.mp4"],
    "callfull": {
      "Introduction": [
        "タイガー ファイヤー サイバー ファイバー",
        "ダイバー バイバー ジャージャー",
        "ファイボー ワイパー ファーマー ジャスパー",
        "ホワイパー クーパー イエスクレイパー ",
        "クレイパー クーパー ホワイパー",
        "ジャスパー ファーマー ワイパー ファイボー ",
        "ジャージャー"
      ],
      "PostChorus": [
        "マルフォイ マルフォイ マルフォイ マルフォイ",
        "あ～👏グリフィンドール",
        "アクシオ レダクト ルーモス",
        "ウィンガー ディア厶 レヴィオーサー",
        "貴方のはレヴィオサー",
        "エクスペクト パトローナム",
        "トムリドル トムリドル",
        "ヴォルデモート って知ってる？"
      ],
      "Verse": [
        "高まるよ 高まるよ",
        "高まる低まる ビスマルク",
        "シジマール アルシンド",
        "カズダンス ニーハイオーハイ",
        "缶チューハイ ウーロンハイ",
        "ナチュラルハイ アイキャンフライ (←ここで飛ぶ)"
      ],
      "Interlude": [
        "人造ファーマ 繊維ジャスパー",
        "ダイバーダイバー ダダダダダイバー",
        "虎火除去飛 虎火除去飛",
        "ミョーホントゥスケ ストライパー",
        "ファイターファイター 人造チャペアペ",
        "除去飛サイダー カラキナワイパー",
        "海女ダイバー 海女ダイバー",
        "ワールドカオス イエッダイバー"
      ],
      "Outro": [
        "言いたいこと があるんだよ",
        "やっぱり〇〇〇が",
        "ゲーエンヴィアー",
        "ティーガァ フォイエル",
        "クゥンスト フィーバー",
        "タゥツァー シュビングング",
        "ヒェーミーファーザー フィリーゲン",
        "バザィティガン ゼーユングファー",
        "ゲッティン ヴァイナハテン エンゲル",
        "アッシェンプッテル ヴンダーランド",
        "フンケ フランメ ポラースシェテルン",
        "プレヤーデン ヘルマンカルツ",
        "カール ハインツ シュナイダー"
      ]
    },
    "lyrics": "少しの風感じて 君と二人同じ夏を過ごせるときに\n波の音を聴きながら確かめてるホントの気持ちでも今がすごく楽しい\n\n水しぶきをあげるテンションではしゃいでる100%の\nシチュエーション最高だねずっと終わらないように\n\nきっとこの夏に捕まえて波に負けないような勢いでI love you!\nちゃんと伝えられるよね\n君のSummer Memory全部全部 上書きしちゃおうかなんて\n言えないけどきっとイチバンだね この瞬間\n明日もきっとそうだよね\n\n潮の匂い漂う 夕焼け空君の隣 特等席だね\n今日もめくる1ページ 明日も\nまた君で埋めたいもっともっと夢の中でも\n\n振りかえると続く足跡が今までを表してるよ\n\n誰にも譲れないからずっと変わらないように\n\nもっとこの夏にゆだねて波を越えるような想い伝えるよ\nドキドキが止まらないけど\n君のSummer memory これからも私色に染めちゃって\nこっちだけ見てずっとイチバンだよね 君にとって\n私だってそうだから\n\nこんな毎日が続いたら他に何もいらないね\n夏日差し浴びてキラキラ 君に届ける\n\nきっとこの夏に捕まえて波に負けないような勢いでI love you!\nちゃんと伝えられるよね\n君のSummer Memory全部全部 上書きしちゃおうかなんて\n言えないけどきっとイチバンだね この瞬間\n明日もきっとそうだよね\n"
  },
  {
    "id": 3,
    "name": "Twinkle☆Stage",
    "rank": "12",
    "mv": "IpuHsPicGe0",
    "live": "qRR-yx0tNx4",
    "call": {
      "Introduction": "萌え萌えキュン発動スタンダード",
      "PostChorus": "ジャパン倍速",
      "Interlude": "ガチ恋口上"
    },
    "calllive": {
      "Introduction": 0,
      "PostChorus": 50,
      "Interlude": 100
    },
    "calljump": {
      "Introduction": 8,
      "PostChorus": 70,
      "Interlude": 120
    },
    "jide": [],
    "callfull": {
      "Introduction": [
        "萌え萌えキュン、萌え萌えキュン",
        "しゃー行くぞ",
        "タイガー ファイヤー サイバー ファイバー",
        "ダイバー バイバー ジャージャー"
      ],
      "PostChorus": ["(倍速)虎 火 人造 繊維 ", "海女 振動 化繊"],
      "Interlude": [
        "言いたいことがあるんだよ",
        "やっぱり◯◯はかわいいよ",
        "すきすき大好きやっぱ好き",
        "やっと見つけたお姫様",
        "俺が生まれてきた理由",
        "それは◯◯に出会うため",
        "俺と一緒に人生歩もう",
        "世界で一番愛してる",
        "あーいーしーてーるー"
      ]
    },
    "lyrics": "幸せにしてあげる\n\nパッと目覚めて窓開けて深呼吸したら\n何気ない特別な今日がSTARTしそうだね\nちょっと落ち込む日もあるよそれでもいいかな\nでもね君の瞳には可愛いく映りたい\n\n知らない世界をもっともっと一緒に\n探そうラビリンス不安定な形でも　\nきっと抜け出せるはずだから\n\nちゃんと愛してね？\n\ntwinkle stage ワクワクしちゃう魔法をかけてあげるよ\n色とりどりの星(スター)から見つけてほしい　君だけにその笑顔を見るために私は輝くよ\nいつまでも一緒にいてね\n\nもっと知りたい頭上のrightそのペンで未来描きたい照らされる愛は私それとも君？\n\n同じ色の輝きが交差してBig Bangワタシ色の宇宙船乗ってどこまでも\n\n寂しがり屋で不器用臆病な心ラビンユー　不完全な私にも溢れる愛をくれた君を\n大切にするよ！\n\ntwinkle stage ドキドキしちゃうこの一瞬を見逃さずに目指したのは一番星今宵(こよい)はどうぞ酔いしれて\n私を大好きな君がずっと微笑んでいつまでも\n幸せでありますように\n\n勇気と優しさ信じることって時には少しの魔法のチカラも必要\n無機質な夜空に光る星たちのイリュージョン叶えたい…！\n\nstage ワクワクしちゃう魔法をかけてあげるよ\n色とりどりの星(スター)から見つけてほしい　君だけに\n\nその笑顔を見るために私は輝くよ\n願うは一つ私の大好きな君がいつまでも\n幸せでありますように"
  },
  {
    "id": 4,
    "name": "ほろ酔い君中毒",
    "rank": "13",
    "mv": "nUFWqFuQmVc",
    "live": "L50yHk3C0TQ",
    "call": {
      "Introduction": "スタンダード",
      "PostChorus": "ジャパニーズ",
      "Interlude": "よいカチン口上",
      "Outro": "バロよいmix"
    },
    "calllive": {
      "Introduction": 0,
      "PostChorus": 60,
      "Interlude": 120,
      "Outro": 180
    },
    "calljump": {
      "Introduction": 5,
      "PostChorus": 70,
      "Interlude": 140,
      "Outro": 192
    },
    "jide": ["4out.mp4"],
    "callfull": {
      "Introduction": [
        "タイガー ファイヤー サイバー ファイバー",
        "ダイバー バイバー ジャージャー"
      ],
      "PostChorus": ["虎 火 人造 繊維", "海女 振動 化繊"],
      "Interlude": [
        "言いたいことは酔いカチン",
        "LIVEの後には生ビール",
        "好き好き大好き鬼殺し",
        "やっと見つけた👏飲み屋",
        "俺が生まれてきた理由",
        "それはお酒に出会うため",
        "俺と一緒にへらへら呑もうな",
        "お酒も〇〇も愛してる！"
      ],
      "Outro": [
        "しゃー飲むぞ! (発動)",
        "ウォッカ ウィスキー",
        "テキーラ ブランデー",
        "ストゼロ スピリッツ",
        "レモンサワー ハイボール",
        "ビール・ワイン・クライナー"
      ]
    },
    "lyrics": "お仕事今日もお疲れ様 やっと待ってた華金\n最初はお決まりの生1つ\n\n｢お酒ばっかじゃなくてこれからみんなはみしゃん中毒もっと大好きになってー｣\n｢みしゃんだけじゃなくりさちも好きになって｣\n\nペースが早い私の瞳を見て飲みすぎとかは\nただまだ決めないで\n酒の波に揺られる、リキュールが踊る奇想天外なストーリー\n\nドキドキ頭の中 おかしくなっちゃうよ\n脳内もう君中毒だよ\nほらクラクラ ドキドキ君の瞳に夢中\nチェイサーなんていらないよ\nほら叫ぶよ\n行くよ、いくよ、みんなも、せーので乾杯\n\n\nグラスが空になる、共に過ごした時間を\nもう酔っちゃった振りをするの\n\n｢毎日飲みたいメロンソーダ｣\n｢今夜も飲みたいレモンサワー｣\n｢みんなドリチケほしいな」\n｢ドリチケちょうだい！ドリンクチケット」\n\nほろ酔いのストーリーを乗せながら\n油断していたふたりの甘い時間\nそれでも飲み放題の時間はまだまだ\n胸がうるさい静かにしてー\n\n恋してる 予想外 好きになっちゃうよ\n重度すぎる依存性だよ\nほら取り扱い注意 力みなぎっても\n10度なんて飲めないよ\nほらいっせーので\n飲むよ、飲むよ、泥酔するよ、乾杯\n\nクラクラ 頭の中 おかしくなっちゃうよ\n脳内もう君中毒\n\nドキドキ頭の中 おかしくなっちゃうよ\n脳内もう君中毒だよ\nほらクラクラ ドキドキ君の瞳に夢中\nチェイサーなんていらないよ\nほら叫ぶよ\n行くよ、いくよ、最後も、みんなで乾杯"
  },
  {
    "id": 5,
    "name": "めんたるのいず",
    "rank": "8",
    "mv": "ACIIxk6JpiE",
    "live": "64XCzqneTks",
    "call": {
      "Introduction": "スタンダード",
      "PostChorus": "虎火発動 ジャパニーズ",
      "Interlude": "タケミンオリジナルパーフェクト",
      "Outro": "時折マーメイド"
    },
    "calllive": {
      "Introduction": 0,
      "PostChorus": 60,
      "Interlude": 100,
      "Outro": 160
    },
    "calljump": {
      "Introduction": 3,
      "PostChorus": 65,
      "Interlude": 130,
      "Outro": 180
    },
    "jide": ["5inter.mp4", "5out.mp4"],
    "callfull": {
      "Introduction": [
        "タイガー ファイヤー サイバー ファイバー",
        "ダイバー バイバー ジャージャー"
      ],
      "PostChorus": [
        "虎虎虎虎*3",
        "虎火",
        "人造 繊維 海女 振動 化繊",
        "飛 除去"
      ],
      "Interlude": [
        "ジャージャー ファイボー ワイパー",
        "ヘルテイ カイザー バーモス",
        "イザナギ イェ！イザナミ",
        "チャカダ ソミュ",
        "ボラル ジェゴ",
        "ホァシェン ラオフー",
        "ジュントイセー"
      ],
      "Outro": [
        "除去 飛 化繊 振動 海女 繊維",
        "振動人造火",
        "虎 火 虎 火",
        "除去除去除去除去",
        "虎火人造繊維",
        "海女 振動 化繊 飛 除去",
        "超 海（かい）舞 農場"
      ]
    },
    "lyrics": "ぐるぐる歯車が回って社会は上手く動いてるらしい\n難しいことよく分かんないし即レスできない\n\nかわいい服着てステージで笑っているけど全て投げ出したくなることあるんだよ\n\nはいはい、そうですね 想像してたより困難でSOSです。\nやられそうなメンタルそんなんばっか ハードモードな人生、、、\n\nCry、Cry、Cry、暗い夜からこの世界とびだして見えない消えたい大体しんどい上ヤバいエンドレスゲーム\n期待したい未来じゃなく今でしょ何より大切なこと\n大好きだから私の事カワイイでしょ？\n\nペチャンコな心押し込んで社会の荒波にダイブして\nギリギリで保ってるテンションがおかしくなりそう\n\nキラキラ写してステージで踊ってるけど\nたまに逃げ出したくなることあるんだよ、、、\n\nそうそう、フォローと拡散希望です。詳しくはSNSで。\nそれはそうとメンタルキツイことばっか ほんと超ムズい人生\n\n嫌い嫌い嫌い狭い部屋からこの世界抜け出して言えない死ねない大体詰みそうだしヤバいエンドレスゲーム\n痛い痛い痛い痛い心が時々涙流しても\n大好きだからみんなの事声聞かせて\n\n手と手合わせ声上げてもっともっと応援してみんな心ひとつにしてプチョヘンザ\n\nCry、Cry、Cry、暗い夜からこの世界とびだして\n何もかも全て上手くいってほしい\n\nCry、Cry、Cry、暗い夜からこの世界とびだして見えない消えたい大体しんどい上ヤバいエンドレスゲーム\n期待したい未来じゃなく今でしょ何より大切なこと\n大好きだから私の事カワイイでしょ？"
  },
  {
    "id": 6,
    "name": "エンドレスラブ",
    "rank": "5",
    "mv": "wf5UO1cnEJ4",
    "live": "_KpuW2aYx6k",
    "call": {
      "Introduction": "旧：ミューホントゥスケ広場+スタンダード（ワイパーまで）新：ミューホントゥスケ広場+キャプ翼キャンセルスタンダードファーマーまで",
      "PostChorus": "闇mixスロー",
      "Interlude": "旧：日アイヌ可変 新：朦月mix"
    },
    "calllive": { "Introduction": 0, "PostChorus": 60, "Interlude": 130 },
    "calljump": { "Introduction": 0, "PostChorus": 85, "Interlude": 160 },
    "jide": [],
    "callfull": {
      "Introduction": [
        "ミョーホントゥスケ 化繊飛除去",
        "ジャージャー ファイボー ワイパー",
        "キタキタキタキタ 沸いてきた",
        "タイガータイガータイガーファイヤー",
        "サイバー ファイバー ダイバー ",
        "バイバー ジャージャー ファイボ ワイパー",
        "ジャンパー ピンガー ダンスファーマー"
      ],

      "PostChorus": [
        "(スロー)",
        "ライガー ファイター サイダー ファインダー",
        "ドライバー ベイベー ジャッジャー バリボーストライパー"
      ],
      "Interlude": [
        "有明（ありあけ）十六夜（いざよい）朧月（おぼろづき）",
        "朔月（さくげつ）三光（さんこう）氷輪（ひょうりん）",
        "月下（げっか）金烏玉兎（きんうぎょくと）",
        "日月星辰（じつげつせいしん）幻月（げんげつ）",
        "無月（むげつ）天満月（あまみつつき）"
      ]
    },
    "lyrics": "ねぇ、お願い私だけを見て逃げられないの Fall in love\n通りすがりのほかの雌（オンナ）に目移りしてる Tastes like shit\nリストカットは毎日かならずしてる安定剤虐めてほしいわけじゃない nm…ごめんね\n\nlonely 気づいてくれないわたしの気持ちは永遠に続いてく\n大好きなの抑えきれない\n\nEndless love おかえりなさいあなた\nわたしはいつもここにいるからネガティブ安定\nEverlasting なんでもするから許して\n会いにきてほしいんです愛されたいんです\nだからお願い妄想slave\n\nスキスキスキスキスしてドキドキドキしてるよ\n嘘だよODなんてしてないちゃんと叱ってほしいの\n\n別れたくないぜったい離れたくないだめだよ\n辛いから辞めてよね nm… ごめんね\n\nlovely 気づいていないのわたしの気持ちは永遠に続いてく\n大好きなの抑えきれない\n\nEndless love 待っていたの大好きなあなた\nわたしはいつもここにいるからポジティブ思考\nEverlasting なんでも指示してください\n会いにきてほしいんです愛されたいんです\nだから私たち妄想slave\n\nいやよやめてよだけど・・・\nそれもイイかももっともっと　もっともっと\n\nEndless love おかえりなさいあなた\nわたしはいつもここにいるからネガティブ安定\n妄想しても満足しないの\n会いにきてほしいんです抱きしめてほしいんです\nずっと永遠に私たち妄想slave"
  },
  {
    "id": 7,
    "name": "嘘つきシンドローム",
    "rank": "6",
    "mv": "UpyB4tiQ2RQ",
    "live": "6bFDG7HtIJ8",
    "call": {
      "Introduction": "タイガーファイヤー始動 スタンダード",
      "PostChorus": "虎火始動 ジャパニーズ",
      "Bridge": "混沌→混沌逆打ち",
      "Outro": "裏スペ逆打ち裏スペキャンセルポルトガル逆打ち"
    },
    "calllive": {
      "Introduction": 0,
      "PostChorus": 65,
      "Bridge": 100,
      "Outro": 140
    },
    "calljump": {
      "Introduction": 8,
      "PostChorus": 68,
      "Bridge": 115,
      "Outro": 168
    },
    "jide": ["7out.mp4"],
    "callfull": {
      "Introduction": [
        "タイタタタイタイ",
        "タイガーファイヤー",
        "サイバー ファイバー ダイバー",
        "バイバー ジャージャー ファイボ ワイパー"
      ],
      "PostChorus": [
        "虎虎虎虎*3",
        "虎火",
        "人造 繊維 海女 振動 化繊",
        "飛 除去"
      ],
      "Bridge": [
        "わ*6 ワールドカオス",
        "諸行 小暮 時雨 神楽 金剛山 翔襲叉",
        "しょ*6 翔襲叉",
        "金剛山 神楽 時雨 木暮 諸行",
        "ワールドカオス"
      ],
      "Outro": [
        "マラビージャス（発動）",
        "パイースデラス エスパンシオン",
        "セニシエンタ アンヘル レノ",
        "ナヴィダ ディオサ シーレナ",
        "ビブラル ブゾ",
        "フィブラ シベル フェゴ ティグレ",
        "バーモス———",
        "ティグレ フェゴ シベル フィブラ",
        "👏エクスクルイル",
        "ヴォアル アルゴダオ ヴィブラサオ",
        "ペスカドーラ フィブラ",
        "アルチフィシャル",
        "フォーグ ティグル",
        "バーモス・ガレーラ"
      ]
    },
    "lyrics": "私感情 いつも 不安定で他人の愛を 求めて\n君の理想 演じて嘘で取り繕って\n\n本音も嘘も 知らないで増えてくいいね 満たされて\nそれでも憂いは 絶えずあって孤独の底に沈んでく\n\nほんとの私 それすらも分からなくなって\n君との距離は 近づいても遠く離れ去ってゆく\n\n君の理想に なるから\nしのごの言わず恋して曖昧なままで愛して\nインスタントな愛でも満たされるから\n純情なんて言えないすぐ見返りを求めてる\nこんな私だけれど 愛してくれますか？\n\n私 曖昧 自己不明瞭だってエゴすら とうに なくなったって\n君の言葉 貰えるならそれで きっといいんだって\n\n本音なんか いらないって感情なんかひた隠して\n君の好きな子になって それが私の幸せ\n\n君が求める 私は 私の中に無い\nでも愛される 為には可愛く演じきらなくちゃ\n\n今まで 誰のためにも なれずに\n無意味な日々を 送ってきた\nこんな私だけど生きる意味もった\n\n嘘偽りだと 言われても\n本音なんかじゃない 言われても\nすべてはあなただけの 為だから\n\nしのごの言わず恋して曖昧なままで愛して\nインスタントな愛でも満たされるから\n純情なんて言えないすぐ見返りを求めてる\nこんな私だけれど 愛してほしい\n君の理想になるわ だから恋をしてね？"
  },
  {
    "id": 8,
    "name": "夏心シークレット",
    "rank": "11",
    "mv": "7AWUOy577O0",
    "live": "nc55spkKyag",
    "call": {
      "Introduction": "スタンダード三連（スタジャパアイヌ3連）",
      "PostChorus": "三角関数キャンセルジャパニーズ (トライアングル…しゃーいくぞ！)",
      "Interlude": "可変三連ワイパーキャンセルver.",
      "Bridge": "混沌MIX",
      "Outro": "花火mix"
    },
    "calllive": {
      "Introduction": 0,
      "PostChorus": 50,
      "Interlude": 150,
      "Bridge": 196,
      "Outro": 220
    },
    "calljump": {
      "Introduction": 5,
      "PostChorus": 90,
      "Interlude": 175,
      "Bridge": 196,
      "Outro": 235
    },
    "jide": ["8post.mp4"],
    "callfull": {
      "Introduction": [
        "タイガー ファイヤー サイバー ファイバー",
        "ダイバー バイバー ジャージャー",
        "ファイボ ゴッデス クリスマス",
        "レインディア エンジェル シンデレラ",
        "エクスパンション ワンダーランド",
        "スパーク フレイム ケージ",
        "ポラリス プレアデス スターリースカイ"
      ],
      "PostChorus": [
        "俺とお前の赤い糸",
        "俺の俺の○○",
        "いやいや*4 俺の○○",
        "サイン コサイン タンジェント",
        "トライアングル しゃーいくぞ",
        "虎 火 人造 繊維",
        "海女 振動 化繊"
      ],
      "Interlude": [
        "人造 ファイヤ ファイボーワイパー",
        "タイガー タイガー タタタタタイガー",
        "チャペアペカラキナ チャペアペカラキナ",
        "ミョーホントゥスケ ワイパー",
        "ワイパーワイパー",
        "いやいやいやいや",
        "ワイパーワイパー 人造繊維 イエッワイパー"
      ],
      "Bridge": [
        "ワ！ワ！ワ！ワ！ワ！ワ！ ワールドカオス！！(発動)",
        "諸行(しょぎょう) 木暮(こぐれ)",
        "時雨(しぐれ)神楽(かぐら)",
        "金剛山(こんごうさん)",
        "翔襲叉(しょうしゅうしゃ)"
      ],
      "Outro": [
        "5,4,3,2,1",
        "菊(きく) 牡丹(ぼたん)",
        "滝(たき) 蜂(はち)",
        "千輪(せんりん)",
        "葉落(ようらく)",
        "冠菊(かむろぎく)"
      ]
    },
    "lyrics": "夏心　「好きだよ」と言えないまま\n\n少しだけ涼しい夜風が吹く\n二人だけの公園　何を話そうか\nちゃんと言ってくれなきゃわからないよ\n好きになったら負けで　もうずるいな\n\n例えば君とお祭りに行って\n花火見たりして　友達卒業したい\n\n夏心　「好きだよ」と言えないまま\nアイスみたいに溶けてしまわない様に\n会いたくて眠れない長い夜は\n声を聞かせてよ　星の空超えて\n素直な気持ちは複雑なシークレット　\n今はまだ\n\n太陽に向かって咲く向日葵\n力の限り夏を彩ってくれる\n少しだけ火照った 日焼けの後\nまるで恋した微熱 君のせいだ\n\nお願い ひとつ約束をしてよ\nまた来る季節も 二人で過ごせるように\n\n夏心  霧がかる恋の森に\nこのまま迷い込んで 帰りたくないよ\n恋しくて 泣き出してしまいそう\n夢の中でさえ 君を探してる\n恋する乙女は 誰だって臆病なの\nわかってよ\n\n宝石を散らした様な雨上がり\n二人きりの世界  おとぎ話みたい\n\n夏心　「好きだよ」と言えないまま\nアイスみたいに溶けてしまわない様に\n会いたくて眠れない長い夜は\n声を聞かせてよ　星の空超えて\n素直な気持ちは複雑なシークレット　\n今はまだ"
  },
  {
    "id": 9,
    "name": "妄想のラビリンス",
    "rank": "2",
    "mv": "oGT29vwr9hs",
    "live": "xNa7vmqgnCk",
    "call": {
      "Introduction": "スタンダードワイパーまで",
      "Chorus": "意味不あいあい(ゴキあい)",
      "PostChorus": "虎火行くよで ジャパニーズ(倍速)",
      "Interlude": "クラップからの アラビア語 ｲｪｯ!ﾏﾝｹﾞ!ｴﾀｰﾅﾙ!",
      "Outro": "アッチェレ終幕ジャパ可変"
    },
    "calllive": {
      "Introduction": 0,
      "Chorus": 40,
      "PostChorus": 70,
      "Interlude": 110,
      "Outro": 180
    },
    "calljump": {
      "Introduction": 5,
      "Chorus": 60,
      "PostChorus": 78,
      "Interlude": 120,
      "Outro": 195
    },
    "jide": ["9inter.mp4", "9out.mp4"],
    "callfull": {
      "Introduction": [
        "タイガー ファイヤー サイバー ファイバー",
        "ダイバー バイバー ジャージャー",
        "ファイボー ワイパー"
      ],
      "Chorus": [
        "アイアイアイアイアイ！ もう一回！",
        "アイアイアイアイ！ アイアイアイアイ！"
      ],
      "PostChorus": ["(倍速)虎 火 人造 繊維 ", "海女 振動 化繊"],
      "Interlude": [
        "スィフリーアスィール (始動)",
        "ナミル ナール スィナーイー ナスィージュ",
        "ガタサ ハッザ ハイトゥンシナーイー",
        "(間奏の最後→)",
        "イエッ！ マンゲ！ エターナル"
      ],
      "Outro": [
        "農場 舞 海鵜（うみう）跳 （ちょう）",
        "（倍速）除去 飛 化繊 振動 海女 繊維 人造 火",
        "虎 火 虎 火",
        "虎 虎 虎 虎（倍速）",
        "虎 火 人造繊維 海女 振動（4倍）",
        "海女振 海女振 海女振動（4倍）",
        "海女繊 海女繊 人造火（4倍）",
        "虎 火 人造 繊維（倍速）👏",
        "海女 振動 化繊 飛 除去 跳 海鵜 舞 農場"
      ]
    },
    "lyrics": "ようこそ 私の世界へご案内\n\n目を閉じて頭の中ふわふわ想い巡らせて\n今夜もいつもの場所へとたどり着いたら始めましょう\n\n脳内世界 壮大な空間 1度入ったら抜け出せない \n今夜も街に眠る頃に夢にお邪魔して連れ去るの\n\n「私だけ見てね」とあなたを閉じ込める\n\nこの美しい幻の螺旋の果てに誘い込む\nここは私の妄想のラビリンス\n夢見てる間少しだけ独り占めしてしまいたいの \nようこそ私の世界へご案内\n\n恋の秘薬 黒の書籍 不安を煽る嫉妬のパフューム \n禁じられた闇のレシピ今宵のディナーを召し上がれ\n\n秘密だよ指切りげんまん 1度破ったら許さない \n明日もみんな起きる頃に記憶は消してあげるからね\n\n夢から忍び込んでアナタを堕とすだけ\n\nこの崩れそうで儚げな輪廻の森に迷い込む\nそこは天国？それとも地獄かしら？\n絡み合う糸を解いても逃げられないくらい深い \n今日こそ私の虜にしてみせる\n\nまた夜が来て夢の中迷宮を彷徨っている\n抜け出せないのは私だった\n\nこの美しい幻の螺旋の果てに誘い込む\nここは私の妄想のラビリンス\n夢見てる間少しだけ独り占めしてしまいたいの \nようこそ私の世界へご案内"
  },
  {
    "id": 10,
    "name": "恋のアカシ",
    "rank": "1",
    "mv": "ogya9Y-vRYk",
    "live": "yKhEHkjv9Xg",
    "call": {
      "Introduction": "ミョーホンドライバー広場 →（短タイガーファイヤー発動)",
      "PostChorus": "虎火発動（トラトラなし）→跳！海鵜！舞農場！",
      "Interlude": "倍速銀河口上ファボリアスター→\n\n倍速可変3連→倍速チスパ可変→七大罪（英語）",
      "Outro": "チャペアペ発動アイヌ晴→カムイ！ホロカプ！アーホイヨ！"
    },
    "calllive": {
      "Introduction": 0,
      "PostChorus": 70,
      "Interlude": 130,
      "Outro": 220
    },
    "calljump": {
      "Introduction": 0,
      "PostChorus": 100,
      "Interlude": 170,
      "Outro": 243
    },
    "jide": ["10in.mp4", "10post.mp4", "10inter.mp4", "10out.mp4"],
    "callfull": {
      "Introduction": [
        "ミョーホン ドライバー",
        "化繊 飛 ライガー",
        "ジャッジャー バリボー ストライパー",
        "(3小節待ち)",
        "タイガーファイヤー",
        "サイバー ファイバー ダイバー",
        "バイバー ジャージャー",
        "ファイボ ワイパー",
        "ジャンパー ピンガー ダンスファーマー"
      ],
      "PostChorus": [
        "(3小節待ち)",
        "虎火(発動)",
        "人造 繊維 海女 振動 化繊",
        "飛 除去 跳 海鵜 舞農場"
      ],
      "Interlude": [
        "(倍速)",
        "銀河に轟く歌声と",
        "地球に花咲くその笑顔",
        "お前が好きだと輝き叫ぶ",
        "行くぜ全力どこまでも",
        "光のごとく駆け巡る",
        "好きじゃねぇ 愛してる",
        "インジョ ジャスパー ビブラル 化繊",
        "イェ ナルダ ファボリアスター",
        "(倍速)",
        "人造ファイヤ ファイボーワイパー",
        "タイガー タイガー タタタタタイガー",
        "チャペアペカラキナ チャペアペカラキナ",
        "ミョーホントゥスケ ワイパー",
        "ファイヤー ファイヤー 虎 虎 カラキナ",
        "チャペアペファーマー 海女 海女 ジャスパー",
        "虎 タイガー 虎 タイガー",
        "人造繊維 イエッタイガー",
        "(倍速)",
        "チスパ ジャーマ 舞農場",
        "チャペ虎タイガー ストライパー",
        "除去飛除去 虎虎虎",
        "振繊除去飛 海女虎火",
        "(七大罪（英語）)",
        "プライド エンビィ ラース スロゥス",
        "グリード グラトニー ラスト"
      ],
      "Outro": [
        "チャペ――― アペ――― (発動)",
        "カラ キナ ララ トゥスケ",
        "ウィスゥペ ケスィ スィスゥパ",
        "カムイ ホロカプ アーホイヨ"
      ]
    },
    "lyrics": "ガラス細工の人形をふたつ並べて飾って\n私たちの愛みたいに縛りつけちゃうわ\n\n風が冷たい街の中　指先を重ね合ったなら\n甘い 甘い 恋の海に　溺れていたい\n\n月の夜　聞こえる鐘の音（ね）窓辺に立って　\n花を千切る手は震えてる 求めるのは恋の証です\n\n\n好きだよって言って言って言って言って\n今すぐずっとずっとずっとずっと愛して\n一人きりにしたりしたら　許してあげない\n抱きしめてギュッとギュッとギュッとギュッと\nキツめにもっともっともっともっと愛して\n傷跡にキスをしたら鎖を解いて\nこの愛は淡く甘くて脆いけど \n世界で一番　キレイなの\n\n\n酷く憂鬱　誰のせい？偽物は全部いらない\nどこか遠く響く声に　怯えているの\n\nどこまでも暗い深淵を覗き込んで\nそこでこの愛を探してよ\n見つかるのは恋のアカシです\n\n私以外　見ないで見ないで一生あの子の方に\n向かないで可愛いのは世界中でわたしだけでしょう？\n永遠にラブ♡ラブ♡ラブ♡ラブ♡続くわ\nクラクラクラクラ酔わせて怪しげな果実食べて　\n魔法にかかるのこの愛はまるで妄想の迷宮\nあなたとわたしの居場所なの\n\n\n好きだよって言って言って言って言って今すぐ\nずっとずっとずっとずっと愛して\n一人きりにしたりしたら　許してあげない\n\n\n抱きしめてギュッとギュッとギュッとギュッとキツめにもっともっともっともっと愛して\n傷跡にキスをしたら鎖を解いて\nこの愛は淡く甘くて脆いけど　\n世界で一番　キレイなの\n"
  },
  {
    "id": 11,
    "name": "恋愛桃源郷",
    "rank": "7",
    "mv": "QakWBpU0FCk",
    "live": "E1CyrXa_fuU",
    "call": {
      "Introduction": "スタンダード",
      "PreChorus": "スタンダードキャンセルスタンダード倍速",
      "Chorus": "意味不ウォーアイニー",
      "PostChorus": "ジャパン",
      "PreChorus2": "ジャパニーズキャンセルジャパニーズ倍速",
      "Interlude": "中国語アッチェレ",
      "Outro": "中国語3連"
    },
    "calllive": {
      "Introduction": 0,
      "PreChorus": 30,
      "Chorus": 49,
      "PostChorus": 60,
      "PreChorus2": 95,
      "Interlude": 120,
      "Outro": 160
    },
    "calljump": {
      "Introduction": 0,
      "PreChorus": 37,
      "Chorus": 47,
      "PostChorus": 70,
      "PreChorus2": 102,
      "Interlude": 131,
      "Outro": 185
    },
    "jide": ["11inter.mp4", "11out.mp4"],
    "callfull": {
      "Introduction": [
        "タイガー ファイヤー サイバー ファイバー",
        "ダイバー バイバー ジャージャー"
      ],
      "PreChorus": [
        "タイガー ファイヤー サイバー ファイバー",
        "(ここから倍速)",
        "タイガー ファイヤー サイバー ファイバー",
        "ダイバー バイバー ジャージャー"
      ],
      "Chorus": ["あⅹ6 ウォーアイニー！", "あいあいあいあいウォーアイニー×2"],
      "PostChorus": ["虎 火 人造 繊維", "海女 振動 化繊"],
      "PreChorus2": [
        "虎 火 人造 繊維",
        "(ここから倍速)",
        "虎 火 人造 繊維",
        "海女 振動 化繊"
      ],
      "Interlude": [
        "ノンチャン ウー ハイチー チャオ",
        "チューチー フェイ フアシェン ジェンドン ハイニー シェンウェイ レンザオ フオ",
        "ラオフー フオ ラオフー フオ",
        "ラオフー ラオフー ラオフー ラオフー (ラオフオレンウェイハイジェンドン)",
        "ハイジェンハイジェン ハイジェンドン ハイシェンハイシェン レンザオフオ",
        "<ラオフー フオ レンザオ シェンウェイ> ハイニー ジェンドン",
        "フアシェン フェイ チューチー チャオ",
        "ハイチー ウー ノンチャン"
      ],
      "Outro": [
        "ウォーメンゾウヴァー(始動)",
        "ラオフー フオ レンザオ",
        "シェンウェイ ハイニー",
        "ジェンドン メェイレンイー",
        "ヌゥーシェン シェンダァンジエ シィンルー",
        "ティェンシ フイグーニャン イーヂォウ",
        "マァンヨウ シイェンチイン",
        "フオフゥア フゥオイェン ベイジーシィン",
        "マオスゥシントゥアン シィンコオン"
      ]
    },
    "lyrics": "もっと愛して恋愛桃源郷\n\nニーハオ　羽を伸ばしチャイナ\n古びたドア開けてみれば\nゆらゆらゆら霞む視界のその先は楽園\nワンシャンハオ　今は夢を見チャイナ\n桃色のスポットライト\nキラキラキラ眩しいここは誰にも邪魔出来ない\n\nこの夜は一度きり聴こえる歌声身を任せ\nもっともっと自由でいいの\n\nここは愛でできた桃源郷　幻想の花の都\n憂き世の傷忘れて　あなたは恋をする\n愛を魅せる桃源郷　甘い視線の誘惑\n迸る情熱を燃やし尽くす場所\nどうぞ　もっと愛して恋愛桃源郷\n\nニーハオ　恋は弱肉強食のんびりはいけないアルメラメラメラ　燃えて焦がれてそのまま灰になれ\nウォアイニー　世界広しといえど\nこんな出会いはもうない\n好き好き好き貴方の推しは妄想slaveで\n\nこの愛は最上級　よそ見は絶対許さない\nずっとずっと　夢中にさせる\n\nここはあなただけの桃源郷　\n謎に包まれた秘境\n心の赴くまま　素敵な恋をする\n迷い込んだ桃源郷\n響き渡るメロディー\nきっとあなたも虜　躊躇いは捨てて\nだから　もっと激しく恋愛桃源郷\n\n剛性や食事と音楽美女が舞い踊る\n永遠に覚めることはない　桃源郷\n\nここは愛でできた桃源郷　\n幻想の花の都\n憂き世の傷忘れて　あなたは恋をする\n愛を魅せる桃源郷　\n甘い視線の誘惑\n迸る情熱を燃やし尽くす場所\nどうぞ　もっと愛して恋愛桃源郷"
  },
  {
    "id": 12,
    "name": "群青トリガー",
    "rank": "4",
    "mv": "cEhkMSwOSmI",
    "live": "BVZ876OwWm8",
    "call": {
      "Introduction": "スタンダード(出来る人はツーステも👍)",
      "PostChorus": "ジャパニーズ (出来る人はツーステも👍)",
      "Interlude": "アイヌ日可変→倍速日本語可変",
      "Outro": "ドイツ1連 (出来る人はツーステも👍)"
    },
    "calllive": {
      "Introduction": 0,
      "PostChorus": 70,
      "Interlude": 100,
      "Outro": 160
    },
    "calljump": {
      "Introduction": 13,
      "PostChorus": 73,
      "Interlude": 110,
      "Outro": 175
    },
    "jide": ["12inter.mp4"],
    "callfull": {
      "Introduction": [
        "タイガー ファイヤー サイバー ファイバー",
        "ダイバー バイバー ジャージャー"
      ],
      "PostChorus": ["虎 火 人造 繊維", "海女 振動 化繊"],
      "Interlude": [
        "ウィスペケスィ",
        "チャペチャペチャペ",
        "チャペアペカラキナカラアペチャペ",
        "除去飛除去 虎虎虎",
        "虎 火 人造 繊維 海女 振動 化繊 飛 除去 飛 化繊 振動 海女 繊維 人造 火(倍速)",
        "人造 火 海女 繊維 化繊 飛 除去(倍速)",
        "除去 飛 除去 飛",
        "化繊振動海女繊維人造火虎"
      ],
      "Outro": [
        "ゲーエンヴィアー",
        "ティーガァ フォイエル",
        "クゥンスト フィーバー",
        "タゥツァー シュビングング",
        "ヒェーミーファーザー フィリーゲン",
        "カールハインツシュナイダー"
      ]
    },
    "lyrics": "二度とないこの時を壊れそうな心を抱いて\nまだ歩いていくよ\n\nもがいていた今日が昨日に変わってて\n戸惑い立ち止まったってもう未来は\n止められない僕は僕じゃないといけないんだ\n臆病なままのこれが僕だよ\n\nちぎれた空の下 差し出す手のひらを\n強く掴んだらもう離さないでね\n\n始発電車 風がすり抜けてく時\n微笑みをくれた それだけで未来は\n何とかなりそうで。壊れそうな心を抱いて\nまだ歩いていくよ\n\nプラットホーム 霞む朝の空気\n足りない空想を指でなぞった\n夢見がちだって事わかっているけど\nいつだって現実はメランコリーだね\n\n誰かの代わりじゃなく 自分だけの歌を\n余裕なんかなくたって輝きたい\n今だって\n\n二度とないこの時を同じこの場所で\n生きていけることそれだけで未来は\nどうにかなりそうな壊れそうな心を抱いて\nまだまだ\n\n始発電車 風がすり抜けてく時\n微笑みをくれた それだけで未来は\nどうにかかなりそうで壊れそうな心を抱いて\nまだ歩いていくよ\n"
  },
  {
    "id": 13,
    "name": "雪空キスシーン",
    "rank": "9",
    "mv": "o7vHG3YDBWs",
    "live": "999jxAi8RyA",
    "call": {
      "Introduction": "スタンダード",
      "Interlude": "六花MIX"
    },
    "calllive": { "Introduction": 0, "Interlude": 60 },
    "calljump": { "Introduction": 30, "Interlude": 175 },
    "jide": [],
    "callfull": {
      "Introduction": [
        "タイガー ファイヤー サイバー ファイバー",
        "ダイバー バイバー ジャージャー"
      ],
      "Interlude": [
        "回(かい) 深(しん) 白(はく) 秋(しゅう)",
        "天華(てんげ) 天花(てんか) 六花(むつのはな)",
        "太平(たびら) 斑(はだれ) 垂り(しずり) 涅槃(ねはん)",
        "冠(かむり) 白魔(はくま) 撓雪(しおりゆき)"
      ]
    },
    "lyrics": "雪がキラキラ　夜に舞い散る暗闇を切り裂く様な白さで\n今は二人でいられる事が私にとっては何よりも大切で\n凍(こご)える唇　触れた雪空キスシーン\n\n街並騒がしく色づいて恋人達 はみんな浮かれているね\n目を見て想いを伝え合う簡単な様で難しいんだな\n\n二人　歩幅を合わせて歩く時は\nねぇずっと繋いだ右手離さないでね\n\n雪がキラキラ　夜に舞い散る 暗闇を切り裂く様な白さで\n今は二人でいられる事が 私にとっては何よりも大切で\n凍(こご)える唇　触れた雪空キスシーン\n\n心が震えてしまう時はあったかい腕の中で眠らせて欲しい眠らせてほしい\n思えばあなたに出会うまでは自分と向き合うこともしなかったから\n\n風が意地悪なくらい冷たいのはそうきっと冬が二人を近づけてるの\n\n月がユラユラ　空に滲んだ 控えめなイルミネーションみたいに\nもしも時間を止められたなら 二人の世界にずっといれるのに\n名前を呼ぶ時　照れるあなたに恋をした\n\n曇る窓　擦ってみたなら 宝石みたいな街が見えるね\n\n想いひとひら　声にならない\n行く宛の知らない二人の恋路\nけれどわたしは笑顔でいるね　\nその輝きが消えてしまわない様に\n\n雪がキラキラ　夜に舞い散る暗闇を切り裂く様な白さで\n今は二人でいられる事が私にとっては何よりも大切で\n凍(こご)える唇　触れた雪空キスシーン"
  }
]
